{"about_index.md":"2632f5bd","about_update.md":"96f1a219","aigc_index.md":"759eabda","aigc_lora_index.md":"d7bf2bd5","aigc_sd_gpt.md":"b555f237","aigc_sd_index.md":"29e964bb","aigc_sd_options.md":"69b7ace5","aigc_video_index.md":"24f87794","challenge_complexity_index.md":"f9bd7577","challenge_complexity_空间复杂度.md":"c41c1ecf","challenge_index.md":"a70e4736","challenge_链表_index.md":"9018b245","challenge_队列.md":"c5e0e8a2","cloudpic_index.md":"2fa44224","gpt_index.md":"7edfc058","index.md":"523a14c4","interview_index.md":"4082d53d","interview_vue_index.md":"873da6ad","interview_vue_vue双向绑定理解.md":"d4df69f4","interview_vue_vue的生命周期.md":"1aa5db9c","interview_vue_实例挂载的过程发生了什么.md":"cc9eb1cb","interview_vue_对spa理解.md":"fc23e61f","interview_vue3_index.md":"7de9275c","interview_vue3_性能提升表现.md":"4e6af24d","interview_重学javascript_index.md":"a8fd6081","sentence-day_index.md":"3d96b56f"}
